gitwebhooks/__init__.py
gitwebhooks/__main__.py
gitwebhooks/server.py
gitwebhooks/auth/__init__.py
gitwebhooks/auth/custom.py
gitwebhooks/auth/factory.py
gitwebhooks/auth/gitee.py
gitwebhooks/auth/github.py
gitwebhooks/auth/gitlab.py
gitwebhooks/auth/verifier.py
gitwebhooks/cli/__init__.py
gitwebhooks/cli/config.py
gitwebhooks/cli/help.py
gitwebhooks/cli/init_wizard.py
gitwebhooks/cli/prompts.py
gitwebhooks/cli/serve.py
gitwebhooks/cli/service.py
gitwebhooks/config/__init__.py
gitwebhooks/config/loader.py
gitwebhooks/config/models.py
gitwebhooks/config/registry.py
gitwebhooks/config/server.py
gitwebhooks/handlers/__init__.py
gitwebhooks/handlers/base.py
gitwebhooks/handlers/custom.py
gitwebhooks/handlers/factory.py
gitwebhooks/handlers/gitee.py
gitwebhooks/handlers/github.py
gitwebhooks/handlers/gitlab.py
gitwebhooks/handlers/request.py
gitwebhooks/logging/__init__.py
gitwebhooks/logging/setup.py
gitwebhooks/main/__init__.py
gitwebhooks/main/__main__.py
gitwebhooks/main/version.py
gitwebhooks/models/__init__.py
gitwebhooks/models/config.py
gitwebhooks/models/provider.py
gitwebhooks/models/request.py
gitwebhooks/models/result.py
gitwebhooks/utils/__init__.py
gitwebhooks/utils/constants.py
gitwebhooks/utils/exceptions.py
gitwebhooks/utils/executor.py
gitwebhooks/utils/systemd.py
gitwebhooks-2.4.0.dist-info/licenses/LICENSE
gitwebhooks-2.4.0.dist-info/METADATA
gitwebhooks-2.4.0.dist-info/WHEEL
gitwebhooks-2.4.0.dist-info/entry_points.txt
gitwebhooks-2.4.0.dist-info/top_level.txt
gitwebhooks-2.4.0.dist-info/RECORD
