Metadata-Version: 2.4
Name: gitwebhooks
Version: 2.4.0
Summary: A lightweight Git webhook server for automated deployment supporting GitHub, Gitee, GitLab, and custom webhooks
Author-email: Troy Tse <troy@holyhi.net>
Maintainer-email: Troy Tse <troy@holyhi.net>
License-Expression: MIT
Project-URL: Homepage, https://github.com/troytse/gitwebhooks
Project-URL: Documentation, https://github.com/troytse/gitwebhooks#readme
Project-URL: Repository, https://github.com/troytse/gitwebhooks.git
Project-URL: Issues, https://github.com/troytse/gitwebhooks/issues
Keywords: webhook,git,github,gitee,gitlab,deployment,automation,server,devops
Classifier: Development Status :: 5 - Production/Stable
Classifier: Environment :: No Input/Output (Daemon)
Classifier: Intended Audience :: Developers
Classifier: Intended Audience :: System Administrators
Classifier: Operating System :: OS Independent
Classifier: Programming Language :: Python :: 3
Classifier: Programming Language :: Python :: 3.6
Classifier: Programming Language :: Python :: 3.7
Classifier: Programming Language :: Python :: 3.8
Classifier: Programming Language :: Python :: 3.9
Classifier: Programming Language :: Python :: 3.10
Classifier: Programming Language :: Python :: 3.11
Classifier: Programming Language :: Python :: 3.12
Classifier: Programming Language :: Python :: 3.13
Classifier: Programming Language :: Python :: 3.14
Classifier: Topic :: Internet :: WWW/HTTP :: HTTP Servers
Classifier: Topic :: Software Development :: Version Control :: Git
Classifier: Topic :: System :: Installation/Setup
Classifier: Topic :: System :: Systems Administration
Classifier: Typing :: Typed
Requires-Python: >=3.6
License-File: LICENSE
Provides-Extra: dev
Requires-Dist: pytest>=6.0; extra == "dev"
Requires-Dist: pytest-cov>=2.0; extra == "dev"
Dynamic: license-file
